{"name":"מורן - תכנות","uuid":"3b411ae0-4cdc-11ea-a58d-bd536c9b6387","sectionsOrdering":"[\"80620fe0-4e4d-11ea-a58d-bd536c9b6387\",\"6db45fc0-4e4c-11ea-a58d-bd536c9b6387\",\"7087fcb0-4e4d-11ea-a58d-bd536c9b6387\"]","user_uuid":"f5717831-f934-11e8-bc66-67c08c330dba","createdAt":"2020-02-11T14:38:55.886Z","updatedAt":"2020-02-13T14:34:48.977Z","sections":[{"name":"פקודות צייר ב-scratch","uuid":"6db45fc0-4e4c-11ea-a58d-bd536c9b6387","lecture_uuid":"3b411ae0-4cdc-11ea-a58d-bd536c9b6387","key":"quiz","value":"{\"question\":\"\",\"timeLimit\":\"200\",\"questionType\":\"single\",\"questionImages\":[\"/upload/3b411ae0-4cdc-11ea-a58d-bd536c9b6387/6db45fc0-4e4c-11ea-a58d-bd536c9b6387_question_1581590499323.PNG\"],\"answers\":[{\"id\":1,\"text\":\"מלבן\",\"image\":\"\",\"truth\":true},{\"id\":2,\"text\":\"משולש\",\"image\":\"\",\"truth\":false},{\"id\":3,\"text\":\"משושה\",\"image\":\"\",\"truth\":false},{\"id\":4,\"text\":\"לא יופיע על המסך דבר\",\"image\":\"\",\"truth\":false},{\"id\":5,\"text\":\"\",\"image\":\"\",\"truth\":false}]}","notes":"עקבו אחר קטע הקוד הנתון, מה לדעתכם יופיע על גבי המסך?","createdAt":"2020-02-13T10:34:35.324Z","updatedAt":"2020-02-13T10:41:40.575Z"},{"name":"פקודות צייר ב-scratch (copy)","uuid":"7087fcb0-4e4d-11ea-a58d-bd536c9b6387","lecture_uuid":"3b411ae0-4cdc-11ea-a58d-bd536c9b6387","key":"quiz","value":"{\"question\":\"\",\"timeLimit\":\"200\",\"questionType\":\"single\",\"questionImages\":[\"/upload/3b411ae0-4cdc-11ea-a58d-bd536c9b6387/6db45fc0-4e4c-11ea-a58d-bd536c9b6387_question_1581590499323.PNG\"],\"answers\":[{\"id\":1,\"text\":\"מלבן\",\"image\":\"\",\"truth\":true},{\"id\":2,\"text\":\"משולש\",\"image\":\"\",\"truth\":false},{\"id\":3,\"text\":\"משושה\",\"image\":\"\",\"truth\":false},{\"id\":4,\"text\":\"לא יופיע על המסך דבר\",\"image\":\"\",\"truth\":false},{\"id\":5,\"text\":\"\",\"image\":\"\",\"truth\":false}]}","notes":"עקבו אחר קטע הקוד הנתון, מה לדעתכם יופיע על גבי המסך?","createdAt":"2020-02-13T10:34:35.324Z","updatedAt":"2020-02-13T10:41:49.564Z"},{"name":"welcome","uuid":"80620fe0-4e4d-11ea-a58d-bd536c9b6387","lecture_uuid":"3b411ae0-4cdc-11ea-a58d-bd536c9b6387","key":"text","value":"{\"text\":\"ברוכים הבאים!\",\"canRespond\":false,\"timeLimit\":\"120\"}","notes":"שלום לכם תלמידים יקרים, אני מאוד שמח שאנחנו נפגשים היום.\nהחלטתי לבדוק את הידע שלכם בסקראץ.\nבואו נראה מה אתם זוכרים ומה הבנתם מפקודת צייר בסקראץ.\nשימו לב, אנחנו משלבים חשיבה מיחשובית, תחומי דעת שונים ממתמטיקה.","createdAt":"2020-02-13T10:42:16.159Z","updatedAt":"2020-02-13T10:44:44.356Z"}],"user":{"id":null,"uuid":"f5717831-f934-11e8-bc66-67c08c330dba","role_id":1,"password":"$2a$08$9LKObGNawgL.Yha4BTuf/O0t1tvqir08hUXQDhqjxpX.pjccvNOBy","status":"Active","email":"super@admin.com","createdAt":"2019-11-13T21:41:47.167Z","updatedAt":"2019-11-13T21:41:47.263Z"}}